README.md
setup.py
remote_jinja/__init__.py
remote_jinja.egg-info/PKG-INFO
remote_jinja.egg-info/SOURCES.txt
remote_jinja.egg-info/dependency_links.txt
remote_jinja.egg-info/requires.txt
remote_jinja.egg-info/top_level.txt