Metadata-Version: 2.1
Name: remote-jinja
Version: 0.1.62
Summary: Handles remote templates for ongoing projects with Jinja
Home-page: https://github.com/akiva10b/remote-jinja.git
Author: Akiva Berger
Author-email: akiva10b@gmail.com
License: UNKNOWN
Platform: UNKNOWN
Classifier: Operating System :: OS Independent
Classifier: Intended Audience :: Developers
Classifier: Programming Language :: Python
Classifier: Programming Language :: Python :: 3.5
Classifier: Programming Language :: Python :: 3.6
Classifier: Programming Language :: Python :: 3.7
Classifier: Programming Language :: Python :: 3.8
Classifier: Programming Language :: Python :: 3.9
Requires-Python: >=3.5.3
